{
    "statistics": {
        "2": {
            "expected": 212.236, 
            "pval": 0.866, 
            "observed": 204
        }, 
        "3": {
            "expected": 92.452, 
            "pval": 0.844, 
            "observed": 87
        }, 
        "4": {
            "expected": 50.272, 
            "pval": 0.9, 
            "observed": 45
        }, 
        "5": {
            "expected": 32.756, 
            "pval": 0.928, 
            "observed": 28
        }, 
        "6": {
            "expected": 23.338, 
            "pval": 0.736, 
            "observed": 22
        }, 
        "7": {
            "expected": 16.708, 
            "pval": 0.384, 
            "observed": 18
        }, 
        "8": {
            "expected": 12.714, 
            "pval": 0.25, 
            "observed": 15
        }, 
        "9": {
            "expected": 9.488, 
            "pval": 0.49, 
            "observed": 10
        }, 
        "10": {
            "expected": 7.502, 
            "pval": 0.298, 
            "observed": 9
        }
    }, 
    "components": [
        [
            "ACKR3", 
            "ALDOA", 
            "ALDOC", 
            "ANK1", 
            "ANKRD1", 
            "ATP1B1", 
            "ATP5F1D", 
            "CLVS2", 
            "CRIP2", 
            "ENO3", 
            "FAM81A", 
            "FRMD3", 
            "FTH1", 
            "IFNA4", 
            "JMJD1C", 
            "MYBPC3", 
            "MYH7", 
            "MYL2", 
            "MYL3", 
            "MYOM1", 
            "MYOM2", 
            "MYOZ2", 
            "NAP1L2", 
            "OBSCN", 
            "PABIR1", 
            "PALLD", 
            "PCYT2", 
            "PDLIM3", 
            "PPP2R2B", 
            "PPP3CB", 
            "PPP3R1", 
            "RCAN1", 
            "SIRT6", 
            "SIX1", 
            "SPTB", 
            "TCAP", 
            "TTC3", 
            "TTN", 
            "ZNF529"
        ], 
        [
            "ADAM9", 
            "C1QA", 
            "C1QB", 
            "C1QC", 
            "CD6", 
            "CLPSL1", 
            "COL4A1", 
            "COL4A2", 
            "COLGALT2", 
            "CREBZF", 
            "FCN1", 
            "FNDC5", 
            "GYG1", 
            "H1-0", 
            "NFE2L1", 
            "NHLRC3", 
            "NUDT15", 
            "PARVA", 
            "PODXL", 
            "PTPRA", 
            "PTS", 
            "PYGB", 
            "RSU1", 
            "STBD1", 
            "XBP1"
        ], 
        [
            "CT45A1", 
            "DCTD", 
            "DMD", 
            "DPPA2", 
            "FGF12", 
            "MRPL48", 
            "MRPL55", 
            "NGRN", 
            "PPP4R2", 
            "PPP4R3B", 
            "PTPA", 
            "RBMS3", 
            "SCN5A", 
            "SNTA1", 
            "SNTB1", 
            "ZNF460"
        ], 
        [
            "CD200R1", 
            "COL1A1", 
            "COL1A2", 
            "COL3A1", 
            "EHD1", 
            "EHD3", 
            "HAND2", 
            "HTRA1", 
            "IMPDH1", 
            "NINJ1", 
            "P4HA2", 
            "PCOLCE", 
            "SCYL1", 
            "SPANXN3", 
            "SPARC"
        ], 
        [
            "LCLAT1", 
            "NDUFB10", 
            "NDUFB2", 
            "NDUFB3", 
            "NDUFB4", 
            "NDUFB6", 
            "NDUFB8", 
            "NDUFB9", 
            "NDUFS4", 
            "NDUFV3", 
            "PRRT2", 
            "PVRIG", 
            "TTC17"
        ], 
        [
            "ARHGAP20", 
            "CYFIP2", 
            "ENSA", 
            "FKBP2", 
            "ITGA5", 
            "ITGB3", 
            "PLG", 
            "RALGDS", 
            "RAP2A", 
            "RAP2B", 
            "RGL1", 
            "THBS1"
        ], 
        [
            "CACNA2D2", 
            "COL14A1", 
            "CPE", 
            "HLA-DQB2", 
            "MUCL1", 
            "NR2F2", 
            "OAF", 
            "OGN", 
            "PRL", 
            "RNASE13", 
            "TM2D3"
        ], 
        [
            "CCR5", 
            "CD4", 
            "CXCL12", 
            "CXCR4", 
            "HACD1", 
            "LDLRAD1", 
            "MYADM", 
            "PTTG1IP", 
            "SLC1A1", 
            "TMEM106C"
        ], 
        [
            "CEBPB", 
            "CIITA", 
            "IL12A", 
            "IL1B", 
            "IL1R1", 
            "IL1RN", 
            "IRF1", 
            "SEC22C", 
            "SPI1", 
            "ZSCAN29"
        ], 
        [
            "COL6A2", 
            "COX6A2", 
            "FSTL1", 
            "NRP1", 
            "PLXND1", 
            "PRRG4", 
            "VEGFA", 
            "VEGFB", 
            "WNT10B"
        ], 
        [
            "ACSF2", 
            "APOC1", 
            "ATP5MJ", 
            "HCFC1R1", 
            "MIDN", 
            "NDUFA2", 
            "NSG2", 
            "SYNGR3"
        ], 
        [
            "ARL8B", 
            "BTN3A3", 
            "CTSL", 
            "CTSV", 
            "CYP2J2", 
            "IKBIP", 
            "MINDY2", 
            "RETSAT"
        ], 
        [
            "CLN5", 
            "GGA3", 
            "IGF2", 
            "IGF2R", 
            "IGFBP1", 
            "IGFBP3", 
            "IGFBP4", 
            "NMRK2"
        ], 
        [
            "DCN", 
            "PLAT", 
            "PLAU", 
            "PPP4R4", 
            "SERPINA5", 
            "SERPINB6", 
            "SERPINE1", 
            "SERPINE2"
        ], 
        [
            "LMOD2", 
            "NOSIP", 
            "TNNC1", 
            "TNNC2", 
            "TNNI3", 
            "TNNT2", 
            "TPM1", 
            "TPM2"
        ], 
        [
            "ADAM17", 
            "CD63", 
            "COL18A1", 
            "COL5A1", 
            "MMP2", 
            "TIMP1", 
            "TIMP3"
        ], 
        [
            "BZW2", 
            "EID3", 
            "MICU2", 
            "NSMCE2", 
            "NSMCE3", 
            "NSMCE4A", 
            "SMDT1"
        ], 
        [
            "CLCNKA", 
            "MEGF8", 
            "PSG1", 
            "PSG3", 
            "PSG5", 
            "SLITRK5", 
            "USF2"
        ], 
        [
            "ALOX5", 
            "COTL1", 
            "HSD17B1", 
            "MAPKAPK2", 
            "ZFP36", 
            "ZFP36L1"
        ], 
        [
            "APMAP", 
            "CLK4", 
            "RASA4", 
            "RGMA", 
            "SAMD4B", 
            "TXNIP"
        ], 
        [
            "ATP6V1A", 
            "ATP6V1B1", 
            "ATP6V1B2", 
            "ATP6V1C1", 
            "ATP6V1E1", 
            "ATP6V1G1"
        ], 
        [
            "GLOD4", 
            "PNRC1", 
            "PNRC2", 
            "PPARGC1A", 
            "RARB", 
            "RORA"
        ], 
        [
            "ABHD17A", 
            "DYNC2I1", 
            "DYNC2LI1", 
            "DYNLT2B", 
            "VSIG8"
        ], 
        [
            "ABHD6", 
            "CKMT2", 
            "ELN", 
            "OLFML3", 
            "TVP23B"
        ], 
        [
            "ARHGAP1", 
            "NKTR", 
            "RAPH1", 
            "RHOC", 
            "SRGAP1"
        ], 
        [
            "CBWD2", 
            "ISCA2", 
            "SERPINC1", 
            "SERPING1", 
            "SUCLG1"
        ], 
        [
            "FGF14", 
            "HOXD12", 
            "MAOB", 
            "NFYA", 
            "NFYB"
        ], 
        [
            "MIX23", 
            "MLYCD", 
            "PAM16", 
            "SLC25A29", 
            "TAMM41"
        ], 
        [
            "AKAP5", 
            "BTBD1", 
            "LIMCH1", 
            "OTUD6B"
        ], 
        [
            "ATOX1", 
            "FAM118A", 
            "MOB3C", 
            "PCYT1A"
        ], 
        [
            "B3GALNT1", 
            "DSG4", 
            "P2RY8", 
            "RNASE7"
        ], 
        [
            "BCL9L", 
            "SSBP3", 
            "SSBP4", 
            "TAL1"
        ], 
        [
            "CANT1", 
            "DPEP2NB", 
            "LRIG1", 
            "NBL1"
        ], 
        [
            "CD33", 
            "PROK2", 
            "SOCS5", 
            "TMBIM1"
        ], 
        [
            "CENPT", 
            "DBI", 
            "PPCDC", 
            "UBXN2A"
        ], 
        [
            "CYTH2", 
            "CYTH3", 
            "INAVA", 
            "IPCEF1"
        ], 
        [
            "EXOC2", 
            "EXOC6B", 
            "FABP3", 
            "SHTN1"
        ], 
        [
            "GMPPA", 
            "GMPPB", 
            "PI4K2B", 
            "PRUNE1"
        ], 
        [
            "IL6", 
            "IL6ST", 
            "LIFR", 
            "OSM"
        ], 
        [
            "INIP", 
            "MTCH1", 
            "NABP1", 
            "NABP2"
        ], 
        [
            "KLKB1", 
            "PDE3A", 
            "PRRG2", 
            "SLFN12"
        ], 
        [
            "KYNU", 
            "MCCD1", 
            "MYL7", 
            "ZNF765"
        ], 
        [
            "L3MBTL1", 
            "RPL36A", 
            "ZKSCAN1", 
            "ZNF146"
        ], 
        [
            "PLAC9", 
            "RAP1A", 
            "RAPGEF5", 
            "RNF213"
        ], 
        [
            "SEPTIN10", 
            "SEPTIN11", 
            "SEPTIN2", 
            "SEPTIN5"
        ], 
        [
            "ADGRL1", 
            "CDKL1", 
            "EDIL3"
        ], 
        [
            "ASAH1", 
            "CAMK1D", 
            "GMFG"
        ], 
        [
            "ATRX", 
            "SMIM40", 
            "SPIN3"
        ], 
        [
            "AUH", 
            "ECHDC2", 
            "IBA57"
        ], 
        [
            "BCL2L14", 
            "TRAPPC1", 
            "TRAPPC10"
        ], 
        [
            "CACNA2D1", 
            "ETFDH", 
            "MYH7B"
        ], 
        [
            "CAPN15", 
            "HERPUD1", 
            "STARD9"
        ], 
        [
            "CBFB", 
            "CHGB", 
            "RUNX3"
        ], 
        [
            "CCDC85A", 
            "RAB27B", 
            "SYTL5"
        ], 
        [
            "CCL22", 
            "CRYAB", 
            "CRYGC"
        ], 
        [
            "CCNY", 
            "CDK14", 
            "CYP51A1"
        ], 
        [
            "CD14", 
            "OASL", 
            "PPP1R12B"
        ], 
        [
            "CDH2", 
            "CNTN1", 
            "PTPRB"
        ], 
        [
            "CENATAC", 
            "TXNL4B", 
            "ZNF114"
        ], 
        [
            "CHMP1B", 
            "MITD1", 
            "TTC33"
        ], 
        [
            "COX7A2", 
            "COX7C", 
            "COX8A"
        ], 
        [
            "CPTP", 
            "PHF13", 
            "TBX20"
        ], 
        [
            "CSPG4", 
            "GTPBP10", 
            "PCBP4"
        ], 
        [
            "CST9", 
            "KCMF1", 
            "MRS2"
        ], 
        [
            "CYBA", 
            "NCF1", 
            "NCF4"
        ], 
        [
            "CYP1A2", 
            "POR", 
            "RABEPK"
        ], 
        [
            "DCAF16", 
            "LDLRAP1", 
            "MAPK8IP3"
        ], 
        [
            "DPP6", 
            "KCND2", 
            "KCNIP2"
        ], 
        [
            "E2F3", 
            "E2F4", 
            "E2F5"
        ], 
        [
            "F12", 
            "HIBCH", 
            "PRORP"
        ], 
        [
            "FAIM", 
            "GLRX", 
            "TRIM62"
        ], 
        [
            "FEZ2", 
            "HEATR5A", 
            "KIF6"
        ], 
        [
            "GABRB2", 
            "GABRB3", 
            "GABRG2"
        ], 
        [
            "HLA-F", 
            "IGKC", 
            "KIR3DL1"
        ], 
        [
            "IDH3A", 
            "NAPSA", 
            "RDH13"
        ], 
        [
            "IGHA1", 
            "IGHM", 
            "JCHAIN"
        ], 
        [
            "IL13", 
            "IL13RA1", 
            "IL13RA2"
        ], 
        [
            "KCNJ2", 
            "KCNJ5", 
            "SDC3"
        ], 
        [
            "LRRFIP1", 
            "LRRFIP2", 
            "TMOD1"
        ], 
        [
            "MRPL16", 
            "MRPL52", 
            "MRPL57"
        ], 
        [
            "NARS1", 
            "NUCB1", 
            "PRXL2B"
        ], 
        [
            "NPPA", 
            "NPPB", 
            "NPR3"
        ], 
        [
            "OAZ1", 
            "RUFY1", 
            "SRA1"
        ], 
        [
            "PDP1", 
            "RPL17", 
            "SNUPN"
        ], 
        [
            "PLA2G3", 
            "PTK2B", 
            "TGFB1I1"
        ], 
        [
            "PNPLA2", 
            "SERPINF1", 
            "UBE2R2"
        ], 
        [
            "RAD51B", 
            "RPAIN", 
            "XRCC2"
        ], 
        [
            "ABI3BP", 
            "GOT1"
        ], 
        [
            "ACOT11", 
            "GEMIN6"
        ], 
        [
            "ADAMTS13", 
            "VWF"
        ], 
        [
            "ADARB1", 
            "ZNF346"
        ], 
        [
            "ADPRS", 
            "HEXD"
        ], 
        [
            "AK1", 
            "PCF11"
        ], 
        [
            "AKR1C2", 
            "ZFP1"
        ], 
        [
            "ALDH1B1", 
            "FEM1B"
        ], 
        [
            "ALS2CL", 
            "RAB22A"
        ], 
        [
            "AMPD1", 
            "AMPD2"
        ], 
        [
            "ANKRD13C", 
            "PTGDR"
        ], 
        [
            "ANKZF1", 
            "NRSN2"
        ], 
        [
            "AQP9", 
            "GAST"
        ], 
        [
            "ARC", 
            "CSRP2"
        ], 
        [
            "AREG", 
            "ICAM1"
        ], 
        [
            "ASXL2", 
            "MBD5"
        ], 
        [
            "ATL1", 
            "PANK2"
        ], 
        [
            "B4GALT1", 
            "OR10G4"
        ], 
        [
            "BTG2", 
            "CNOT8"
        ], 
        [
            "C1R", 
            "C1S"
        ], 
        [
            "C2CD2", 
            "SEC14L1"
        ], 
        [
            "C7", 
            "C8G"
        ], 
        [
            "CCDC112", 
            "LURAP1"
        ], 
        [
            "CCNG2", 
            "PPP2R5C"
        ], 
        [
            "CD151", 
            "CD9"
        ], 
        [
            "CDAN1", 
            "UBN1"
        ], 
        [
            "CDC14B", 
            "GRHPR"
        ], 
        [
            "CFH", 
            "CFHR1"
        ], 
        [
            "CHD2", 
            "ELOA2"
        ], 
        [
            "CHRNA3", 
            "CHRNB4"
        ], 
        [
            "CLDN14", 
            "PLEKHA1"
        ], 
        [
            "CLIC4", 
            "CLIC5"
        ], 
        [
            "CNN2", 
            "CNN3"
        ], 
        [
            "COA1", 
            "SLC23A2"
        ], 
        [
            "COG5", 
            "COG7"
        ], 
        [
            "COL4A4", 
            "FGD6"
        ], 
        [
            "COMMD1", 
            "COMMD4"
        ], 
        [
            "COQ2", 
            "NDUFAF2"
        ], 
        [
            "COX6C", 
            "COX7B"
        ], 
        [
            "CREBL2", 
            "CREBRF"
        ], 
        [
            "CYP11A1", 
            "FDX1"
        ], 
        [
            "DAO", 
            "DAOA"
        ], 
        [
            "DCBLD2", 
            "MFSD4B"
        ], 
        [
            "DDX58", 
            "RNF125"
        ], 
        [
            "DENND11", 
            "SETBP1"
        ], 
        [
            "DEXI", 
            "PEX16"
        ], 
        [
            "DPY19L2", 
            "GUK1"
        ], 
        [
            "EBF1", 
            "ERO1A"
        ], 
        [
            "EDEM2", 
            "FBLN7"
        ], 
        [
            "EDNRA", 
            "SYNGR2"
        ], 
        [
            "EMC10", 
            "EMC3"
        ], 
        [
            "EML1", 
            "ISG20L2"
        ], 
        [
            "EPHB4", 
            "ZSCAN5A"
        ], 
        [
            "ESYT2", 
            "MAPK15"
        ], 
        [
            "FAM126B", 
            "PDCL2"
        ], 
        [
            "FAM241A", 
            "SGCD"
        ], 
        [
            "FAM83B", 
            "PFKFB2"
        ], 
        [
            "FBLN5", 
            "LOXL1"
        ], 
        [
            "FOXN3", 
            "HRNR"
        ], 
        [
            "GABPA", 
            "ZC2HC1B"
        ], 
        [
            "GABRB1", 
            "NEUROD4"
        ], 
        [
            "GAN", 
            "ZC3H13"
        ], 
        [
            "GATA4", 
            "NKX2-5"
        ], 
        [
            "GATD3A", 
            "PPM1K"
        ], 
        [
            "GCC2", 
            "TTC4"
        ], 
        [
            "GINS1", 
            "TIPIN"
        ], 
        [
            "GSDMB", 
            "IGFBP2"
        ], 
        [
            "GZMB", 
            "SRGN"
        ], 
        [
            "H2BW1", 
            "PPP1R2B"
        ], 
        [
            "HID1", 
            "RCN3"
        ], 
        [
            "HLA-DRA", 
            "HLA-DRB1"
        ], 
        [
            "HLA-G", 
            "LILRB2"
        ], 
        [
            "HRC", 
            "ZNF699"
        ], 
        [
            "HSPB6", 
            "UBR3"
        ], 
        [
            "HSPB7", 
            "HSPB8"
        ], 
        [
            "IFNGR1", 
            "SLC9A6"
        ], 
        [
            "IFRD1", 
            "TCEAL4"
        ], 
        [
            "IFT172", 
            "TTC30B"
        ], 
        [
            "KANSL2", 
            "ZNF609"
        ], 
        [
            "KCNAB2", 
            "KCNAB3"
        ], 
        [
            "KLF8", 
            "SGSM3"
        ], 
        [
            "LAMTOR1", 
            "LAMTOR4"
        ], 
        [
            "LDB3", 
            "NPC2"
        ], 
        [
            "LEO1", 
            "TCEA3"
        ], 
        [
            "LUM", 
            "SLIT2"
        ], 
        [
            "MDH1", 
            "TBCA"
        ], 
        [
            "MRNIP", 
            "PKIA"
        ], 
        [
            "MSL1", 
            "MSL3"
        ], 
        [
            "MXI1", 
            "PEAR1"
        ], 
        [
            "MYOF", 
            "SCARB2"
        ], 
        [
            "MZT2B", 
            "TUBGCP6"
        ], 
        [
            "NFIX", 
            "ZNF614"
        ], 
        [
            "NPRL3", 
            "SZT2"
        ], 
        [
            "PAM", 
            "UBR2"
        ], 
        [
            "PCARE", 
            "UFM1"
        ], 
        [
            "PDAP1", 
            "PELI1"
        ], 
        [
            "PIGA", 
            "PIGP"
        ], 
        [
            "PLEKHG5", 
            "RND3"
        ], 
        [
            "PLK3", 
            "RAD52"
        ], 
        [
            "PPA1", 
            "WIPI1"
        ], 
        [
            "PPWD1", 
            "WDR70"
        ], 
        [
            "PRPF38B", 
            "SLTM"
        ], 
        [
            "PRPF39", 
            "TRNAU1AP"
        ], 
        [
            "PRRG3", 
            "RNF149"
        ], 
        [
            "PSMG3", 
            "PSMG4"
        ], 
        [
            "RAB11FIP1", 
            "RELT"
        ], 
        [
            "RAB12", 
            "RILPL1"
        ], 
        [
            "RAB19", 
            "VCAN"
        ], 
        [
            "RAD1", 
            "RAD17"
        ], 
        [
            "RASL10A", 
            "RIC8B"
        ], 
        [
            "REV1", 
            "REV3L"
        ], 
        [
            "RTL8C", 
            "SERPINA7"
        ], 
        [
            "SHE", 
            "TRIT1"
        ], 
        [
            "SOHLH1", 
            "STH"
        ], 
        [
            "SPATA2L", 
            "TDP1"
        ], 
        [
            "TMEM159", 
            "ZNF391"
        ], 
        [
            "TMEM59", 
            "TYW1"
        ]
    ], 
    "parameters": {
        "display_name_file": null, 
        "display_score_file": null, 
        "deltas": [], 
        "verbose": 1, 
        "heat_permutations": 500, 
        "num_cores": -1, 
        "network_permutations": 500, 
        "output_directory": "/ix/djishnu/Hanxi/MI_Spatial/network_analysis/hotnet2/053124_Control/CD68_hotnet_out", 
        "heat_files": [
            "/ix/djishnu/Hanxi/MI_Spatial/network_analysis/hotnet2/053124_Control/CD_68_control.txt"
        ], 
        "output_hierarchy": false, 
        "consensus_permutations": 0, 
        "delta": 0.2118336769310465, 
        "min_cc_size": 2, 
        "network_files": [
            "/ix/djishnu/Priyamvada/Immport/Network_analysis/Networks/Networks_to_run_hotnet/HomoSapiens_binary_co_complex_Feb2023_1_ppr_0.4.h5"
        ], 
        "network_name": "HomoSapiens_binary_co_complex_Feb2023", 
        "permuted_network_paths": [
            "/ix/djishnu/Priyamvada/Immport/Network_analysis/Networks/Networks_to_run_hotnet/permuted_networks/HomoSapiens_binary_co_complex_Feb2023_1_ppr_0.4_##NUM##.h5"
        ], 
        "heat_name": "CD_68_control"
    }, 
    "sizes": {
        "2": 117, 
        "3": 42, 
        "4": 17, 
        "5": 6, 
        "6": 4, 
        "39": 1, 
        "8": 5, 
        "9": 1, 
        "10": 2, 
        "11": 1, 
        "12": 1, 
        "13": 1, 
        "15": 1, 
        "16": 1, 
        "7": 3, 
        "25": 1
    }
}